{
    "id": 306,
    "name": "crush-claw",
    "accuracy": 95,
    "power": 75,
    "pp": 10,
    "priority": 0,
    "damage_class": "physical",
    "type": "normal",
    "target": "selected-pokemon",
    "generation": "generation-iii",
    "effect_chance": 50,
    "effect": "Inflicts regular damage. Has a 50% chance to lower the target’s Defense by one stage.",
    "short_effect": "Has a 50% chance to lower the target’s Defense by one stage.",
    "flavor_text": "Tears at the foe with sharp claws. May lower DEFENSE.",
    "learned_by_pokemon": [
        "sandshrew",
        "sandslash",
        "rhyhorn",
        "kangaskhan",
        "cyndaquil",
        "sneasel",
        "treecko",
        "torchic",
        "combusken",
        "blaziken",
        "slakoth",
        "zangoose",
        "anorith",
        "armaldo",
        "drilbur",
        "excadrill",
        "eelektross",
        "druddigon",
        "rufflet",
        "braviary",
        "rockruff",
        "type-null",
        "silvally",
        "gouging-fire",
        "kangaskhan-mega",
        "pikachu-sinnoh-cap",
        "sandshrew-alola",
        "sandslash-alola",
        "rockruff-own-tempo",
        "lycanroc-dusk",
        "braviary-hisui"
    ],
    "stat_changes": [
        {
            "change": -1,
            "stat": "defense"
        }
    ]
}