{
    "id": 887,
    "name": "hyper-drill",
    "source_url": "https://pokeapi.co/api/v2/move/887/",
    "accuracy": 100,
    "power": 100,
    "pp": 5,
    "priority": 0,
    "damage_class": "physical",
    "type": "normal",
    "target": "selected-pokemon",
    "generation": "generation-ix",
    "effect_chance": null,
    "effect": null,
    "short_effect": null,
    "flavor_text": {
        "scarlet_violet": "The user spins the pointed part of its body at high speed to pierce the target. This attack can hit a target using a move such as Protect or Detect."
    },
    "stat_changes": [],
    "machine": null,
    "metadata": {}
}