{
    "id": 460,
    "name": "spacial-rend",
    "accuracy": 95,
    "power": 100,
    "pp": 5,
    "priority": 0,
    "damage_class": "special",
    "type": "dragon",
    "target": "selected-pokemon",
    "generation": "generation-iv",
    "effect_chance": null,
    "effect": "Inflicts regular damage. User’s critical hit rate is one level higher when using this move.",
    "short_effect": "Has an increased chance for a critical hit.",
    "flavor_text": "The user tears the foe along with the space around it. This move has a high critical-hit ratio.",
    "learned_by_pokemon": [
        "palkia",
        "palkia-origin"
    ],
    "stat_changes": []
}