{
    "name": "aromatic-mist",
    "accuracy": null,
    "damage_class": "status",
    "power": null,
    "pp": 20,
    "priority": 0,
    "target": "ally",
    "type": "fairy",
    "effect_chance": null,
    "effect_changes": [],
    "effect": "Raises a selected ally's Special Defense by one stage.",
    "flavor_text_entries": {
        "x-y": "The user raises the Sp. Def stat of an ally\nPok\u00e9mon by using a mysterious aroma.",
        "omega-ruby-alpha-sapphire": "The user raises the Sp. Def stat of an ally\nPok\u00e9mon by using a mysterious aroma.",
        "sun-moon": "The user raises the Sp. Def stat of an ally Pok\u00e9mon\nby using a mysterious aroma.",
        "ultra-sun-ultra-moon": "The user raises the Sp. Def stat of an ally Pok\u00e9mon\nby using a mysterious aroma.",
        "lets-go-pikachu-lets-go-eevee": "The user raises the Sp. Def stat of an ally Pok\u00e9mon\nby using a mysterious aroma.",
        "sword-shield": "The user raises the Sp. Def stat of an ally Pok\u00e9mon\nby using a mysterious aroma."
    },
    "meta": {
        "ailment": {
            "name": "none",
            "url": "https://pokeapi.co/api/v2/move-ailment/0/"
        },
        "ailment_chance": 0,
        "category": {
            "name": "net-good-stats",
            "url": "https://pokeapi.co/api/v2/move-category/2/"
        },
        "crit_rate": 0,
        "drain": 0,
        "flinch_chance": 0,
        "healing": 0,
        "max_hits": null,
        "max_turns": null,
        "min_hits": null,
        "min_turns": null,
        "stat_chance": 0
    },
    "stat_changes": [
        {
            "change": 1,
            "stat": {
                "name": "special-defense",
                "url": "https://pokeapi.co/api/v2/stat/5/"
            }
        }
    ],
    "generation": "generation-vi",
    "learned_by": [
        "vespiquen",
        "aromatisse",
        "popplio",
        "cutiefly",
        "ribombee",
        "bounsweet",
        "steenee",
        "tsareena",
        "tapu-lele",
        "sinistea",
        "polteageist",
        "hatenna",
        "hattrem",
        "hatterene",
        "milcery",
        "alcremie",
        "weezing-galar"
    ],
    "machines": {}
}