{
    "id": 53,
    "name": "persian",
    "species": "persian",
    "is_default": true,
    "source_url": "https://pokeapi.co/api/v2/pokemon/53/",
    "types": [
        "normal"
    ],
    "abilities": [
        {
            "name": "technician",
            "is_hidden": false,
            "slot": 1
        },
        {
            "name": "technician",
            "is_hidden": false,
            "slot": 2
        },
        {
            "name": "unnerve",
            "is_hidden": true,
            "slot": 3
        }
    ],
    "stats": {
        "hp": 65,
        "attack": 70,
        "defense": 60,
        "special-attack": 65,
        "special-defense": 65,
        "speed": 115
    },
    "ev_yield": [
        {
            "stat": "speed",
            "effort": 2
        }
    ],
    "height": 10,
    "weight": 320,
    "cries": {
        "latest": "https://raw.githubusercontent.com/PokeAPI/cries/main/cries/pokemon/latest/53.ogg",
        "legacy": "https://raw.githubusercontent.com/PokeAPI/cries/main/cries/pokemon/legacy/53.ogg"
    },
    "sprites": {
        "back_default": "https://raw.githubusercontent.com/PokeAPI/sprites/master/sprites/pokemon/back/53.png",
        "back_shiny": "https://raw.githubusercontent.com/PokeAPI/sprites/master/sprites/pokemon/back/shiny/53.png",
        "front_default": "https://raw.githubusercontent.com/PokeAPI/sprites/master/sprites/pokemon/53.png",
        "front_shiny": "https://raw.githubusercontent.com/PokeAPI/sprites/master/sprites/pokemon/shiny/53.png",
        "other": {
            "dream_world": {
                "front_default": "https://raw.githubusercontent.com/PokeAPI/sprites/master/sprites/pokemon/other/dream-world/53.svg",
                "front_female": null
            },
            "home": {
                "front_default": "https://raw.githubusercontent.com/PokeAPI/sprites/master/sprites/pokemon/other/home/53.png",
                "front_female": null,
                "front_shiny": "https://raw.githubusercontent.com/PokeAPI/sprites/master/sprites/pokemon/other/home/shiny/53.png",
                "front_shiny_female": null
            },
            "official-artwork": {
                "front_default": "https://raw.githubusercontent.com/PokeAPI/sprites/master/sprites/pokemon/other/official-artwork/53.png",
                "front_shiny": "https://raw.githubusercontent.com/PokeAPI/sprites/master/sprites/pokemon/other/official-artwork/shiny/53.png"
            },
            "showdown": {
                "back_default": "https://raw.githubusercontent.com/PokeAPI/sprites/master/sprites/pokemon/other/showdown/back/53.gif",
                "back_female": null,
                "back_shiny": "https://raw.githubusercontent.com/PokeAPI/sprites/master/sprites/pokemon/other/showdown/back/shiny/53.gif",
                "back_shiny_female": null,
                "front_default": "https://raw.githubusercontent.com/PokeAPI/sprites/master/sprites/pokemon/other/showdown/53.gif",
                "front_female": null,
                "front_shiny": "https://raw.githubusercontent.com/PokeAPI/sprites/master/sprites/pokemon/other/showdown/shiny/53.gif",
                "front_shiny_female": null
            }
        },
        "versions": {
            "emerald": {
                "front_default": "https://raw.githubusercontent.com/PokeAPI/sprites/master/sprites/pokemon/versions/generation-iii/emerald/53.png",
                "front_shiny": "https://raw.githubusercontent.com/PokeAPI/sprites/master/sprites/pokemon/versions/generation-iii/emerald/shiny/53.png"
            },
            "firered-leafgreen": {
                "back_default": "https://raw.githubusercontent.com/PokeAPI/sprites/master/sprites/pokemon/versions/generation-iii/firered-leafgreen/back/53.png",
                "back_shiny": "https://raw.githubusercontent.com/PokeAPI/sprites/master/sprites/pokemon/versions/generation-iii/firered-leafgreen/back/shiny/53.png",
                "front_default": "https://raw.githubusercontent.com/PokeAPI/sprites/master/sprites/pokemon/versions/generation-iii/firered-leafgreen/53.png",
                "front_shiny": "https://raw.githubusercontent.com/PokeAPI/sprites/master/sprites/pokemon/versions/generation-iii/firered-leafgreen/shiny/53.png"
            },
            "ruby-sapphire": {
                "back_default": "https://raw.githubusercontent.com/PokeAPI/sprites/master/sprites/pokemon/versions/generation-iii/ruby-sapphire/back/53.png",
                "back_shiny": "https://raw.githubusercontent.com/PokeAPI/sprites/master/sprites/pokemon/versions/generation-iii/ruby-sapphire/back/shiny/53.png",
                "front_default": "https://raw.githubusercontent.com/PokeAPI/sprites/master/sprites/pokemon/versions/generation-iii/ruby-sapphire/53.png",
                "front_shiny": "https://raw.githubusercontent.com/PokeAPI/sprites/master/sprites/pokemon/versions/generation-iii/ruby-sapphire/shiny/53.png"
            }
        }
    },
    "base_experience": 148,
    "base_happiness": 70,
    "capture_rate": 90,
    "hatch_counter": 20,
    "gender_rate": 4,
    "has_gender_differences": false,
    "is_baby": false,
    "is_legendary": false,
    "is_mythical": false,
    "pokedex_numbers": {
        "national": 53
    },
    "color": "yellow",
    "shape": "quadruped",
    "egg_groups": [
        "ground"
    ],
    "flavor_text": "Although its fur has many admirers, it is tough to raise as a pet because of its fickle meanness.",
    "genus": "Classy Cat Pokémon",
    "generation": "generation-i",
    "evolution_chain": {
        "species_name": "meowth",
        "evolves_to": [
            {
                "species_name": "persian",
                "evolution_details": {
                    "item": null,
                    "trigger": "level-up",
                    "gender": null,
                    "held_item": null,
                    "known_move": null,
                    "known_move_type": null,
                    "location": null,
                    "min_level": 28,
                    "min_happiness": null,
                    "min_beauty": null,
                    "min_affection": null,
                    "needs_overworld_rain": false,
                    "party_species": null,
                    "party_type": null,
                    "relative_physical_stats": null,
                    "time_of_day": "",
                    "trade_species": null,
                    "turn_upside_down": false
                },
                "evolves_to": []
            },
            {
                "species_name": "perrserker",
                "evolution_details": {
                    "item": null,
                    "trigger": "level-up",
                    "gender": null,
                    "held_item": null,
                    "known_move": null,
                    "known_move_type": null,
                    "location": null,
                    "min_level": 28,
                    "min_happiness": null,
                    "min_beauty": null,
                    "min_affection": null,
                    "needs_overworld_rain": false,
                    "party_species": null,
                    "party_type": null,
                    "relative_physical_stats": null,
                    "time_of_day": "",
                    "trade_species": null,
                    "turn_upside_down": false
                },
                "evolves_to": []
            }
        ]
    },
    "held_items": {},
    "moves": {
        "level-up": [
            {
                "name": "pay-day",
                "level_learned_at": 20,
                "version_groups": [
                    "colosseum",
                    "emerald",
                    "ruby-sapphire",
                    "xd"
                ]
            },
            {
                "name": "pay-day",
                "level_learned_at": 18,
                "version_groups": [
                    "firered-leafgreen"
                ]
            },
            {
                "name": "scratch",
                "level_learned_at": 1,
                "version_groups": [
                    "colosseum",
                    "emerald",
                    "firered-leafgreen",
                    "ruby-sapphire",
                    "xd"
                ]
            },
            {
                "name": "bite",
                "level_learned_at": 1,
                "version_groups": [
                    "colosseum",
                    "emerald",
                    "firered-leafgreen",
                    "ruby-sapphire",
                    "xd"
                ]
            },
            {
                "name": "bite",
                "level_learned_at": 11,
                "version_groups": [
                    "colosseum",
                    "emerald",
                    "ruby-sapphire",
                    "xd"
                ]
            },
            {
                "name": "bite",
                "level_learned_at": 10,
                "version_groups": [
                    "firered-leafgreen"
                ]
            },
            {
                "name": "growl",
                "level_learned_at": 1,
                "version_groups": [
                    "colosseum",
                    "emerald",
                    "firered-leafgreen",
                    "ruby-sapphire",
                    "xd"
                ]
            },
            {
                "name": "screech",
                "level_learned_at": 38,
                "version_groups": [
                    "colosseum",
                    "emerald",
                    "ruby-sapphire",
                    "xd"
                ]
            },
            {
                "name": "screech",
                "level_learned_at": 34,
                "version_groups": [
                    "firered-leafgreen"
                ]
            },
            {
                "name": "fury-swipes",
                "level_learned_at": 46,
                "version_groups": [
                    "colosseum",
                    "emerald",
                    "ruby-sapphire",
                    "xd"
                ]
            },
            {
                "name": "fury-swipes",
                "level_learned_at": 42,
                "version_groups": [
                    "firered-leafgreen"
                ]
            },
            {
                "name": "slash",
                "level_learned_at": 53,
                "version_groups": [
                    "colosseum",
                    "emerald",
                    "ruby-sapphire",
                    "xd"
                ]
            },
            {
                "name": "slash",
                "level_learned_at": 49,
                "version_groups": [
                    "firered-leafgreen"
                ]
            },
            {
                "name": "feint-attack",
                "level_learned_at": 29,
                "version_groups": [
                    "colosseum",
                    "emerald",
                    "ruby-sapphire",
                    "xd"
                ]
            },
            {
                "name": "feint-attack",
                "level_learned_at": 25,
                "version_groups": [
                    "firered-leafgreen"
                ]
            },
            {
                "name": "swagger",
                "level_learned_at": 61,
                "version_groups": [
                    "firered-leafgreen"
                ]
            },
            {
                "name": "fake-out",
                "level_learned_at": 59,
                "version_groups": [
                    "colosseum",
                    "emerald",
                    "ruby-sapphire",
                    "xd"
                ]
            },
            {
                "name": "fake-out",
                "level_learned_at": 55,
                "version_groups": [
                    "firered-leafgreen"
                ]
            }
        ],
        "machine": [
            {
                "name": "cut",
                "level_learned_at": 0,
                "version_groups": [
                    "colosseum",
                    "emerald",
                    "firered-leafgreen",
                    "ruby-sapphire",
                    "xd"
                ]
            },
            {
                "name": "roar",
                "level_learned_at": 0,
                "version_groups": [
                    "colosseum",
                    "emerald",
                    "firered-leafgreen",
                    "ruby-sapphire",
                    "xd"
                ]
            },
            {
                "name": "hyper-beam",
                "level_learned_at": 0,
                "version_groups": [
                    "colosseum",
                    "emerald",
                    "firered-leafgreen",
                    "ruby-sapphire",
                    "xd"
                ]
            },
            {
                "name": "thunderbolt",
                "level_learned_at": 0,
                "version_groups": [
                    "colosseum",
                    "emerald",
                    "firered-leafgreen",
                    "ruby-sapphire",
                    "xd"
                ]
            },
            {
                "name": "thunder",
                "level_learned_at": 0,
                "version_groups": [
                    "colosseum",
                    "emerald",
                    "firered-leafgreen",
                    "ruby-sapphire",
                    "xd"
                ]
            },
            {
                "name": "dig",
                "level_learned_at": 0,
                "version_groups": [
                    "colosseum",
                    "emerald",
                    "firered-leafgreen",
                    "ruby-sapphire",
                    "xd"
                ]
            },
            {
                "name": "toxic",
                "level_learned_at": 0,
                "version_groups": [
                    "colosseum",
                    "emerald",
                    "firered-leafgreen",
                    "ruby-sapphire",
                    "xd"
                ]
            },
            {
                "name": "double-team",
                "level_learned_at": 0,
                "version_groups": [
                    "colosseum",
                    "emerald",
                    "firered-leafgreen",
                    "ruby-sapphire",
                    "xd"
                ]
            },
            {
                "name": "flash",
                "level_learned_at": 0,
                "version_groups": [
                    "colosseum",
                    "emerald",
                    "firered-leafgreen",
                    "ruby-sapphire",
                    "xd"
                ]
            },
            {
                "name": "rest",
                "level_learned_at": 0,
                "version_groups": [
                    "colosseum",
                    "emerald",
                    "firered-leafgreen",
                    "ruby-sapphire",
                    "xd"
                ]
            },
            {
                "name": "thief",
                "level_learned_at": 0,
                "version_groups": [
                    "colosseum",
                    "emerald",
                    "firered-leafgreen",
                    "ruby-sapphire",
                    "xd"
                ]
            },
            {
                "name": "protect",
                "level_learned_at": 0,
                "version_groups": [
                    "colosseum",
                    "emerald",
                    "firered-leafgreen",
                    "ruby-sapphire",
                    "xd"
                ]
            },
            {
                "name": "attract",
                "level_learned_at": 0,
                "version_groups": [
                    "colosseum",
                    "emerald",
                    "firered-leafgreen",
                    "ruby-sapphire",
                    "xd"
                ]
            },
            {
                "name": "return",
                "level_learned_at": 0,
                "version_groups": [
                    "colosseum",
                    "emerald",
                    "firered-leafgreen",
                    "ruby-sapphire",
                    "xd"
                ]
            },
            {
                "name": "frustration",
                "level_learned_at": 0,
                "version_groups": [
                    "colosseum",
                    "emerald",
                    "firered-leafgreen",
                    "ruby-sapphire",
                    "xd"
                ]
            },
            {
                "name": "iron-tail",
                "level_learned_at": 0,
                "version_groups": [
                    "colosseum",
                    "emerald",
                    "firered-leafgreen",
                    "ruby-sapphire",
                    "xd"
                ]
            },
            {
                "name": "hidden-power",
                "level_learned_at": 0,
                "version_groups": [
                    "colosseum",
                    "emerald",
                    "firered-leafgreen",
                    "ruby-sapphire",
                    "xd"
                ]
            },
            {
                "name": "rain-dance",
                "level_learned_at": 0,
                "version_groups": [
                    "colosseum",
                    "emerald",
                    "firered-leafgreen",
                    "ruby-sapphire",
                    "xd"
                ]
            },
            {
                "name": "sunny-day",
                "level_learned_at": 0,
                "version_groups": [
                    "colosseum",
                    "emerald",
                    "firered-leafgreen",
                    "ruby-sapphire",
                    "xd"
                ]
            },
            {
                "name": "shadow-ball",
                "level_learned_at": 0,
                "version_groups": [
                    "colosseum",
                    "emerald",
                    "firered-leafgreen",
                    "ruby-sapphire",
                    "xd"
                ]
            },
            {
                "name": "torment",
                "level_learned_at": 0,
                "version_groups": [
                    "colosseum",
                    "emerald",
                    "firered-leafgreen",
                    "ruby-sapphire",
                    "xd"
                ]
            },
            {
                "name": "facade",
                "level_learned_at": 0,
                "version_groups": [
                    "colosseum",
                    "emerald",
                    "firered-leafgreen",
                    "ruby-sapphire",
                    "xd"
                ]
            },
            {
                "name": "taunt",
                "level_learned_at": 0,
                "version_groups": [
                    "colosseum",
                    "emerald",
                    "firered-leafgreen",
                    "ruby-sapphire",
                    "xd"
                ]
            },
            {
                "name": "snatch",
                "level_learned_at": 0,
                "version_groups": [
                    "colosseum",
                    "emerald",
                    "firered-leafgreen",
                    "ruby-sapphire",
                    "xd"
                ]
            },
            {
                "name": "secret-power",
                "level_learned_at": 0,
                "version_groups": [
                    "colosseum",
                    "emerald",
                    "firered-leafgreen",
                    "ruby-sapphire",
                    "xd"
                ]
            },
            {
                "name": "aerial-ace",
                "level_learned_at": 0,
                "version_groups": [
                    "colosseum",
                    "emerald",
                    "firered-leafgreen",
                    "ruby-sapphire",
                    "xd"
                ]
            },
            {
                "name": "shock-wave",
                "level_learned_at": 0,
                "version_groups": [
                    "colosseum",
                    "emerald",
                    "firered-leafgreen",
                    "ruby-sapphire",
                    "xd"
                ]
            },
            {
                "name": "water-pulse",
                "level_learned_at": 0,
                "version_groups": [
                    "colosseum",
                    "emerald",
                    "firered-leafgreen",
                    "ruby-sapphire",
                    "xd"
                ]
            }
        ],
        "tutor": [
            {
                "name": "body-slam",
                "level_learned_at": 0,
                "version_groups": [
                    "emerald",
                    "firered-leafgreen",
                    "xd"
                ]
            },
            {
                "name": "double-edge",
                "level_learned_at": 0,
                "version_groups": [
                    "emerald",
                    "firered-leafgreen",
                    "xd"
                ]
            },
            {
                "name": "mimic",
                "level_learned_at": 0,
                "version_groups": [
                    "emerald",
                    "firered-leafgreen",
                    "xd"
                ]
            },
            {
                "name": "defense-curl",
                "level_learned_at": 0,
                "version_groups": [
                    "emerald"
                ]
            },
            {
                "name": "swift",
                "level_learned_at": 0,
                "version_groups": [
                    "emerald"
                ]
            },
            {
                "name": "dream-eater",
                "level_learned_at": 0,
                "version_groups": [
                    "emerald",
                    "firered-leafgreen",
                    "xd"
                ]
            },
            {
                "name": "substitute",
                "level_learned_at": 0,
                "version_groups": [
                    "emerald",
                    "firered-leafgreen",
                    "xd"
                ]
            },
            {
                "name": "nightmare",
                "level_learned_at": 0,
                "version_groups": [
                    "xd"
                ]
            },
            {
                "name": "snore",
                "level_learned_at": 0,
                "version_groups": [
                    "emerald"
                ]
            },
            {
                "name": "mud-slap",
                "level_learned_at": 0,
                "version_groups": [
                    "emerald"
                ]
            },
            {
                "name": "icy-wind",
                "level_learned_at": 0,
                "version_groups": [
                    "emerald",
                    "xd"
                ]
            },
            {
                "name": "endure",
                "level_learned_at": 0,
                "version_groups": [
                    "emerald"
                ]
            },
            {
                "name": "swagger",
                "level_learned_at": 0,
                "version_groups": [
                    "emerald",
                    "xd"
                ]
            },
            {
                "name": "sleep-talk",
                "level_learned_at": 0,
                "version_groups": [
                    "emerald"
                ]
            },
            {
                "name": "psych-up",
                "level_learned_at": 0,
                "version_groups": [
                    "emerald"
                ]
            }
        ]
    },
    "forms": [
        "persian",
        "persian-alola"
    ]
}