{
    "id": 55,
    "name": "hustle",
    "source_url": "https://pokeapi.co/api/v2/ability/55/",
    "is_main_series": true,
    "effect": {
        "black-white": "Has no overworld effect.",
        "black-2-white-2": "Has no overworld effect."
    },
    "short_effect": "Strengthens physical moves to inflict 1.5× damage, but decreases their accuracy to 0.8×.",
    "flavor_text": {
        "black-white": "Boosts the Attack stat, but lowers accuracy.",
        "black-2-white-2": "Boosts the Attack stat, but lowers accuracy."
    }
}