{
    "id": 671,
    "name": "spotlight",
    "source_url": "https://pokeapi.co/api/v2/move/671/",
    "accuracy": {
        "sword_shield": null,
        "the_isle_of_armor": null,
        "the_crown_tundra": null,
        "brilliant_diamond_and_shining_pearl": null,
        "legends_arceus": null
    },
    "power": {
        "sword_shield": null,
        "the_isle_of_armor": null,
        "the_crown_tundra": null,
        "brilliant_diamond_and_shining_pearl": null,
        "legends_arceus": null
    },
    "pp": {
        "sword_shield": 15,
        "the_isle_of_armor": 15,
        "the_crown_tundra": 15,
        "brilliant_diamond_and_shining_pearl": 15,
        "legends_arceus": 15
    },
    "priority": 3,
    "damage_class": "status",
    "type": {
        "sword_shield": "normal",
        "the_isle_of_armor": "normal",
        "the_crown_tundra": "normal",
        "brilliant_diamond_and_shining_pearl": "normal",
        "legends_arceus": "normal"
    },
    "target": "selected-pokemon",
    "generation": "generation-vii",
    "effect_chance": {
        "sword_shield": null,
        "the_isle_of_armor": null,
        "the_crown_tundra": null,
        "brilliant_diamond_and_shining_pearl": null,
        "legends_arceus": null
    },
    "effect": {
        "sword_shield": "For the duration of the turn, if the target is also a valid target for a move used by one of its opponents, that move will target it instead.",
        "the_isle_of_armor": "For the duration of the turn, if the target is also a valid target for a move used by one of its opponents, that move will target it instead.",
        "the_crown_tundra": "For the duration of the turn, if the target is also a valid target for a move used by one of its opponents, that move will target it instead.",
        "brilliant_diamond_and_shining_pearl": "For the duration of the turn, if the target is also a valid target for a move used by one of its opponents, that move will target it instead.",
        "legends_arceus": "For the duration of the turn, if the target is also a valid target for a move used by one of its opponents, that move will target it instead."
    },
    "short_effect": {
        "sword_shield": "Forces the target’s opponents to aim at the target for the rest of the turn.",
        "the_isle_of_armor": "Forces the target’s opponents to aim at the target for the rest of the turn.",
        "the_crown_tundra": "Forces the target’s opponents to aim at the target for the rest of the turn.",
        "brilliant_diamond_and_shining_pearl": "Forces the target’s opponents to aim at the target for the rest of the turn.",
        "legends_arceus": "Forces the target’s opponents to aim at the target for the rest of the turn."
    },
    "flavor_text": {
        "sword_shield": "This move can’t be used. It’s recommended that this move is forgotten. Once forgotten, this move can’t be remembered."
    },
    "stat_changes": [],
    "machine": null,
    "metadata": {
        "ailment": "none",
        "category": "unique",
        "min_hits": null,
        "max_hits": null,
        "min_turns": null,
        "max_turns": null,
        "drain": 0,
        "healing": 0,
        "crit_rate": 0,
        "ailment_chance": 0,
        "flinch_chance": 0,
        "stat_chance": 0
    }
}